[{"amount":150000,"_id":"ord001","nama":"buku","price":50000,"quantity":3,"status":"available"}, {"amount":200000,"_id":"ord002","nama":"buku","price":50000,"quantity":4,"status":"available"}, {"amount":100000,"_id":"ord003","nama":"buku","price":50000,"quantity":2,"status":"available"}, {"amount":400000,"_id":"ord004","nama":"tas","price":200000,"quantity":2,"status":"available"}, {"amount":1000000,"_id":"ord005","nama":"tas","price":250000,"quantity":4,"status":"available"}, {"amount":300000,"_id":"ord006","nama":"dompet","price":100000,"quantity":3,"status":"available"}, {"amount":250000,"_id":"ord007","nama":"dompet","price":125000,"quantity":2,"status":"available"}, {"amount":100000,"_id":"ord008","nama":"stempel","price":50000,"quantity":2,"status":"out of stock"}]